distance/__init__.py
distance/fields.py
distance/forms.py
distance/models.py
distance/tests.py
distance/validators.py
distance/migrations/0001_initial.py
distance/migrations/0002_testmodel_no_unit_field.py
distance/migrations/__init__.py
django_distance_field-1.2.5.dist-info/LICENSE
django_distance_field-1.2.5.dist-info/METADATA
django_distance_field-1.2.5.dist-info/WHEEL
django_distance_field-1.2.5.dist-info/top_level.txt
django_distance_field-1.2.5.dist-info/RECORD
