Metadata-Version: 2.1
Name: django-distance-field
Version: 1.2.5
Summary: Django model field to allow storage of a distance (with units).
Home-page: https://bitbucket.org/squarehost/django-distance-field
Author: Ian Shurmer
Author-email: ian@squarehost.co.uk
Classifier: Programming Language :: Python :: 2
Classifier: Programming Language :: Python :: 3
Classifier: Framework :: Django
Classifier: License :: OSI Approved :: MIT License
Classifier: Operating System :: OS Independent
License-File: LICENSE
Requires-Dist: django (>=1.7)
Requires-Dist: six (>=1.11.0)
